setup.cfg
setup.py
edit_line_ranges.egg-info/PKG-INFO
edit_line_ranges.egg-info/SOURCES.txt
edit_line_ranges.egg-info/dependency_links.txt
edit_line_ranges.egg-info/entry_points.txt
edit_line_ranges.egg-info/requires.txt
edit_line_ranges.egg-info/top_level.txt
lineranges/__init__.py
lineranges/cli.py
lineranges/lineranges.py
lineranges/parse_settings.py