Metadata-Version: 1.1
Name: edit-line-ranges
Version: 0.1
Summary: bulk change multiple lines in a text file
Home-page: https://github.com/davethecipo/edit-line-ranges
Author: Davide Olianas
Author-email: ubuntupk@gmail.com
License: UNKNOWN
Download-URL: https://github.com/davethecipo/edit-line-ranges/tarball/0.1
Platform: UNKNOWN
